{
  "data": [
    {
      "x": [1, 2, 3, 4, 5, 6, 7, 8, 9, 10, 11, 12, 13, 14, 15, 16, 17, 18, 19, 20],
      "y": [0, -0.109204407645448, -0.101211902601293, -0.0824298936992605, -0.0541514670630698, -0.0388029446116517, -0.0270568610354777, -0.0220060414086492, -0.015298091726643, -0.0113537689189049, -0.0130316575397561, -0.00985327356593453, -0.00969402584136526, -0.00456213561813651, -0.00580536805427626, -0.00447170988828675, -0.00466388989518052, -0.00318317017594592, -0.0028001836051839, -0.00126639824036057],
      "mode": "lines",
      "showlegend": false,
      "line": {
        "color": "red"
      },
      "hovertemplate": ["<i>Year<i>: %{x} <br>Productivity Change: %{y:.3f}", "<i>Year<i>: %{x} <br>Productivity Change: %{y:.3f}", "<i>Year<i>: %{x} <br>Productivity Change: %{y:.3f}", "<i>Year<i>: %{x} <br>Productivity Change: %{y:.3f}", "<i>Year<i>: %{x} <br>Productivity Change: %{y:.3f}", "<i>Year<i>: %{x} <br>Productivity Change: %{y:.3f}", "<i>Year<i>: %{x} <br>Productivity Change: %{y:.3f}", "<i>Year<i>: %{x} <br>Productivity Change: %{y:.3f}", "<i>Year<i>: %{x} <br>Productivity Change: %{y:.3f}", "<i>Year<i>: %{x} <br>Productivity Change: %{y:.3f}", "<i>Year<i>: %{x} <br>Productivity Change: %{y:.3f}", "<i>Year<i>: %{x} <br>Productivity Change: %{y:.3f}", "<i>Year<i>: %{x} <br>Productivity Change: %{y:.3f}", "<i>Year<i>: %{x} <br>Productivity Change: %{y:.3f}", "<i>Year<i>: %{x} <br>Productivity Change: %{y:.3f}", "<i>Year<i>: %{x} <br>Productivity Change: %{y:.3f}", "<i>Year<i>: %{x} <br>Productivity Change: %{y:.3f}", "<i>Year<i>: %{x} <br>Productivity Change: %{y:.3f}", "<i>Year<i>: %{x} <br>Productivity Change: %{y:.3f}", "<i>Year<i>: %{x} <br>Productivity Change: %{y:.3f}"],
      "name": "Negative Shock<br>Low Productivity",
      "type": "scatter",
      "marker": {
        "color": "rgba(31,119,180,1)",
        "line": {
          "color": "rgba(31,119,180,1)"
        }
      },
      "error_y": {
        "color": "rgba(31,119,180,1)"
      },
      "error_x": {
        "color": "rgba(31,119,180,1)"
      },
      "xaxis": "x",
      "yaxis": "y",
      "frame": null
    },
    {
      "x": [1, 2, 3, 4, 5, 6, 7, 8, 9, 10, 11, 12, 13, 14, 15, 16, 17, 18, 19, 20],
      "y": [0, -0.125550756608002, -0.11582950485727, -0.0966161036114262, -0.0837176925472848, -0.0662815191135811, -0.055080057552341, -0.0460314739035277, -0.0389763722612234, -0.0328559342895997, -0.0252406142788951, -0.0192810473719729, -0.0205070828290638, -0.0171559311127937, -0.0122350116529469, -0.0148534448934488, -0.00875530899480225, -0.00845005319484429, -0.00270646684378183, -0.00520327160566976],
      "mode": "lines",
      "showlegend": false,
      "line": {
        "color": "green"
      },
      "hovertemplate": ["<i>Year<i>: %{x} <br>Productivity Change: %{y:.3f}", "<i>Year<i>: %{x} <br>Productivity Change: %{y:.3f}", "<i>Year<i>: %{x} <br>Productivity Change: %{y:.3f}", "<i>Year<i>: %{x} <br>Productivity Change: %{y:.3f}", "<i>Year<i>: %{x} <br>Productivity Change: %{y:.3f}", "<i>Year<i>: %{x} <br>Productivity Change: %{y:.3f}", "<i>Year<i>: %{x} <br>Productivity Change: %{y:.3f}", "<i>Year<i>: %{x} <br>Productivity Change: %{y:.3f}", "<i>Year<i>: %{x} <br>Productivity Change: %{y:.3f}", "<i>Year<i>: %{x} <br>Productivity Change: %{y:.3f}", "<i>Year<i>: %{x} <br>Productivity Change: %{y:.3f}", "<i>Year<i>: %{x} <br>Productivity Change: %{y:.3f}", "<i>Year<i>: %{x} <br>Productivity Change: %{y:.3f}", "<i>Year<i>: %{x} <br>Productivity Change: %{y:.3f}", "<i>Year<i>: %{x} <br>Productivity Change: %{y:.3f}", "<i>Year<i>: %{x} <br>Productivity Change: %{y:.3f}", "<i>Year<i>: %{x} <br>Productivity Change: %{y:.3f}", "<i>Year<i>: %{x} <br>Productivity Change: %{y:.3f}", "<i>Year<i>: %{x} <br>Productivity Change: %{y:.3f}", "<i>Year<i>: %{x} <br>Productivity Change: %{y:.3f}"],
      "name": "Negative Shock<br>Medium Productivity",
      "type": "scatter",
      "marker": {
        "color": "rgba(255,127,14,1)",
        "line": {
          "color": "rgba(255,127,14,1)"
        }
      },
      "error_y": {
        "color": "rgba(255,127,14,1)"
      },
      "error_x": {
        "color": "rgba(255,127,14,1)"
      },
      "xaxis": "x2",
      "yaxis": "y",
      "frame": null
    },
    {
      "x": [1, 2, 3, 4, 5, 6, 7, 8, 9, 10, 11, 12, 13, 14, 15, 16, 17, 18, 19, 20],
      "y": [0, -0.173757267198392, -0.154325083691419, -0.130849672195154, -0.107220081805139, -0.0947371328457031, -0.077564685167906, -0.064713399147509, -0.0535357351518024, -0.0476848737773083, -0.0376914173558189, -0.0350292194924009, -0.0267898275315809, -0.026192383920602, -0.0164015438139121, -0.0182817211927229, -0.0140092595980333, -0.0123397792522226, -0.00732128248632598, -0.00708915010738088],
      "mode": "lines",
      "showlegend": false,
      "line": {
        "color": "blue"
      },
      "hovertemplate": ["<i>Year<i>: %{x} <br>Productivity Change: %{y:.3f}", "<i>Year<i>: %{x} <br>Productivity Change: %{y:.3f}", "<i>Year<i>: %{x} <br>Productivity Change: %{y:.3f}", "<i>Year<i>: %{x} <br>Productivity Change: %{y:.3f}", "<i>Year<i>: %{x} <br>Productivity Change: %{y:.3f}", "<i>Year<i>: %{x} <br>Productivity Change: %{y:.3f}", "<i>Year<i>: %{x} <br>Productivity Change: %{y:.3f}", "<i>Year<i>: %{x} <br>Productivity Change: %{y:.3f}", "<i>Year<i>: %{x} <br>Productivity Change: %{y:.3f}", "<i>Year<i>: %{x} <br>Productivity Change: %{y:.3f}", "<i>Year<i>: %{x} <br>Productivity Change: %{y:.3f}", "<i>Year<i>: %{x} <br>Productivity Change: %{y:.3f}", "<i>Year<i>: %{x} <br>Productivity Change: %{y:.3f}", "<i>Year<i>: %{x} <br>Productivity Change: %{y:.3f}", "<i>Year<i>: %{x} <br>Productivity Change: %{y:.3f}", "<i>Year<i>: %{x} <br>Productivity Change: %{y:.3f}", "<i>Year<i>: %{x} <br>Productivity Change: %{y:.3f}", "<i>Year<i>: %{x} <br>Productivity Change: %{y:.3f}", "<i>Year<i>: %{x} <br>Productivity Change: %{y:.3f}", "<i>Year<i>: %{x} <br>Productivity Change: %{y:.3f}"],
      "name": "Negative Shock<br>High Productivity",
      "type": "scatter",
      "marker": {
        "color": "rgba(44,160,44,1)",
        "line": {
          "color": "rgba(44,160,44,1)"
        }
      },
      "error_y": {
        "color": "rgba(44,160,44,1)"
      },
      "error_x": {
        "color": "rgba(44,160,44,1)"
      },
      "xaxis": "x3",
      "yaxis": "y",
      "frame": null
    },
    {
      "x": [1, 2, 3, 4, 5, 6, 7, 8, 9, 10, 11, 12, 13, 14, 15, 16, 17, 18, 19, 20],
      "y": [0, 0.230246584280227, 0.213576769414219, 0.18182443255107, 0.139741143719879, 0.112976151635651, 0.0908068377379969, 0.0721226911707494, 0.0565497643094823, 0.0491566386069807, 0.0390745266545094, 0.0371357958621184, 0.0308074141684731, 0.0212412393024559, 0.0197629250502545, 0.0200703254180644, 0.0128243537137199, 0.0104794579268861, 0.00529302870425886, 0.0080377947960673],
      "mode": "lines",
      "showlegend": false,
      "line": {
        "color": "red"
      },
      "hovertemplate": ["<i>Year<i>: %{x} <br>Productivity Change: %{y:.3f}", "<i>Year<i>: %{x} <br>Productivity Change: %{y:.3f}", "<i>Year<i>: %{x} <br>Productivity Change: %{y:.3f}", "<i>Year<i>: %{x} <br>Productivity Change: %{y:.3f}", "<i>Year<i>: %{x} <br>Productivity Change: %{y:.3f}", "<i>Year<i>: %{x} <br>Productivity Change: %{y:.3f}", "<i>Year<i>: %{x} <br>Productivity Change: %{y:.3f}", "<i>Year<i>: %{x} <br>Productivity Change: %{y:.3f}", "<i>Year<i>: %{x} <br>Productivity Change: %{y:.3f}", "<i>Year<i>: %{x} <br>Productivity Change: %{y:.3f}", "<i>Year<i>: %{x} <br>Productivity Change: %{y:.3f}", "<i>Year<i>: %{x} <br>Productivity Change: %{y:.3f}", "<i>Year<i>: %{x} <br>Productivity Change: %{y:.3f}", "<i>Year<i>: %{x} <br>Productivity Change: %{y:.3f}", "<i>Year<i>: %{x} <br>Productivity Change: %{y:.3f}", "<i>Year<i>: %{x} <br>Productivity Change: %{y:.3f}", "<i>Year<i>: %{x} <br>Productivity Change: %{y:.3f}", "<i>Year<i>: %{x} <br>Productivity Change: %{y:.3f}", "<i>Year<i>: %{x} <br>Productivity Change: %{y:.3f}", "<i>Year<i>: %{x} <br>Productivity Change: %{y:.3f}"],
      "name": "Positive Shock<br>Low Productivity",
      "type": "scatter",
      "marker": {
        "color": "rgba(214,39,40,1)",
        "line": {
          "color": "rgba(214,39,40,1)"
        }
      },
      "error_y": {
        "color": "rgba(214,39,40,1)"
      },
      "error_x": {
        "color": "rgba(214,39,40,1)"
      },
      "xaxis": "x",
      "yaxis": "y2",
      "frame": null
    },
    {
      "x": [1, 2, 3, 4, 5, 6, 7, 8, 9, 10, 11, 12, 13, 14, 15, 16, 17, 18, 19, 20],
      "y": [0, 0.137328471080551, 0.124841134413747, 0.104956912781781, 0.0890798776496668, 0.0782242854131762, 0.0643051278129464, 0.0528300412447471, 0.0439745864299968, 0.0390143724820299, 0.0291047250009717, 0.0295889259208948, 0.0241406653426703, 0.0229564199708255, 0.0142106803993157, 0.0139833099267297, 0.0132264069570388, 0.0106947110315819, 0.00751100774635152, 0.00638602675205089],
      "mode": "lines",
      "showlegend": false,
      "line": {
        "color": "green"
      },
      "hovertemplate": ["<i>Year<i>: %{x} <br>Productivity Change: %{y:.3f}", "<i>Year<i>: %{x} <br>Productivity Change: %{y:.3f}", "<i>Year<i>: %{x} <br>Productivity Change: %{y:.3f}", "<i>Year<i>: %{x} <br>Productivity Change: %{y:.3f}", "<i>Year<i>: %{x} <br>Productivity Change: %{y:.3f}", "<i>Year<i>: %{x} <br>Productivity Change: %{y:.3f}", "<i>Year<i>: %{x} <br>Productivity Change: %{y:.3f}", "<i>Year<i>: %{x} <br>Productivity Change: %{y:.3f}", "<i>Year<i>: %{x} <br>Productivity Change: %{y:.3f}", "<i>Year<i>: %{x} <br>Productivity Change: %{y:.3f}", "<i>Year<i>: %{x} <br>Productivity Change: %{y:.3f}", "<i>Year<i>: %{x} <br>Productivity Change: %{y:.3f}", "<i>Year<i>: %{x} <br>Productivity Change: %{y:.3f}", "<i>Year<i>: %{x} <br>Productivity Change: %{y:.3f}", "<i>Year<i>: %{x} <br>Productivity Change: %{y:.3f}", "<i>Year<i>: %{x} <br>Productivity Change: %{y:.3f}", "<i>Year<i>: %{x} <br>Productivity Change: %{y:.3f}", "<i>Year<i>: %{x} <br>Productivity Change: %{y:.3f}", "<i>Year<i>: %{x} <br>Productivity Change: %{y:.3f}", "<i>Year<i>: %{x} <br>Productivity Change: %{y:.3f}"],
      "name": "Positive Shock<br>Medium Productivity",
      "type": "scatter",
      "marker": {
        "color": "rgba(148,103,189,1)",
        "line": {
          "color": "rgba(148,103,189,1)"
        }
      },
      "error_y": {
        "color": "rgba(148,103,189,1)"
      },
      "error_x": {
        "color": "rgba(148,103,189,1)"
      },
      "xaxis": "x2",
      "yaxis": "y2",
      "frame": null
    },
    {
      "x": [1, 2, 3, 4, 5, 6, 7, 8, 9, 10, 11, 12, 13, 14, 15, 16, 17, 18, 19, 20],
      "y": [0, 0.146031537079131, 0.12459712182308, 0.096855074065937, 0.0806623806185174, 0.0682445986915765, 0.0599967323801073, 0.0480016280944721, 0.0402154737456808, 0.0305916451415053, 0.0287306621451891, 0.0239366003209997, 0.0217972288870415, 0.0188635189278563, 0.0170776559806123, 0.00928508632831593, 0.00894664758724711, 0.00927517794805752, 0.00899285482621035, 0.00753915110860858],
      "mode": "lines",
      "showlegend": false,
      "line": {
        "color": "blue"
      },
      "hovertemplate": ["<i>Year<i>: %{x} <br>Productivity Change: %{y:.3f}", "<i>Year<i>: %{x} <br>Productivity Change: %{y:.3f}", "<i>Year<i>: %{x} <br>Productivity Change: %{y:.3f}", "<i>Year<i>: %{x} <br>Productivity Change: %{y:.3f}", "<i>Year<i>: %{x} <br>Productivity Change: %{y:.3f}", "<i>Year<i>: %{x} <br>Productivity Change: %{y:.3f}", "<i>Year<i>: %{x} <br>Productivity Change: %{y:.3f}", "<i>Year<i>: %{x} <br>Productivity Change: %{y:.3f}", "<i>Year<i>: %{x} <br>Productivity Change: %{y:.3f}", "<i>Year<i>: %{x} <br>Productivity Change: %{y:.3f}", "<i>Year<i>: %{x} <br>Productivity Change: %{y:.3f}", "<i>Year<i>: %{x} <br>Productivity Change: %{y:.3f}", "<i>Year<i>: %{x} <br>Productivity Change: %{y:.3f}", "<i>Year<i>: %{x} <br>Productivity Change: %{y:.3f}", "<i>Year<i>: %{x} <br>Productivity Change: %{y:.3f}", "<i>Year<i>: %{x} <br>Productivity Change: %{y:.3f}", "<i>Year<i>: %{x} <br>Productivity Change: %{y:.3f}", "<i>Year<i>: %{x} <br>Productivity Change: %{y:.3f}", "<i>Year<i>: %{x} <br>Productivity Change: %{y:.3f}", "<i>Year<i>: %{x} <br>Productivity Change: %{y:.3f}"],
      "name": "Positive Shock<br>High Productivity",
      "type": "scatter",
      "marker": {
        "color": "rgba(140,86,75,1)",
        "line": {
          "color": "rgba(140,86,75,1)"
        }
      },
      "error_y": {
        "color": "rgba(140,86,75,1)"
      },
      "error_x": {
        "color": "rgba(140,86,75,1)"
      },
      "xaxis": "x3",
      "yaxis": "y2",
      "frame": null
    }
  ],
  "layout": {
    "xaxis": {
      "domain": [0, 0.313333333333333],
      "automargin": true,
      "title": "Years",
      "titlefont": {
        "size": 18
      },
      "tickfont": {
        "size": 14
      },
      "anchor": "y2"
    },
    "xaxis2": {
      "domain": [0.353333333333333, 0.646666666666667],
      "automargin": true,
      "title": "Years",
      "titlefont": {
        "size": 18
      },
      "tickfont": {
        "size": 14
      },
      "anchor": "y2"
    },
    "xaxis3": {
      "domain": [0.686666666666667, 1],
      "automargin": true,
      "title": "Years",
      "titlefont": {
        "size": 18
      },
      "tickfont": {
        "size": 14
      },
      "anchor": "y2"
    },
    "yaxis2": {
      "domain": [0, 0.48],
      "automargin": true,
      "title": "Productivity (No R&D)",
      "titlefont": {
        "size": 18
      },
      "tickfont": {
        "size": 14
      },
      "range": [
        -0.173757267198392,
        0.230246584280227
      ],
      "anchor": "x"
    },
    "yaxis": {
      "domain": [0.52, 1],
      "automargin": true,
      "title": "Productivity (No R&D)",
      "titlefont": {
        "size": 18
      },
      "tickfont": {
        "size": 14
      },
      "range": [
        -0.173757267198392,
        0.230246584280227
      ],
      "anchor": "x"
    },
    "annotations": [],
    "shapes": [
      {
        "type": "line",
        "y0": 0,
        "y1": 0,
        "xref": "paper",
        "x0": 0,
        "x1": 0.313333333333333,
        "line": {
          "color": "red",
          "dash": "dot"
        },
        "yref": "y"
      },
      {
        "type": "line",
        "y0": 0,
        "y1": 0,
        "xref": "paper",
        "x0": 0.353333333333333,
        "x1": 0.646666666666667,
        "line": {
          "color": "red",
          "dash": "dot"
        },
        "yref": "y"
      },
      {
        "type": "line",
        "y0": 0,
        "y1": 0,
        "xref": "paper",
        "x0": 0.686666666666667,
        "x1": 1,
        "line": {
          "color": "red",
          "dash": "dot"
        },
        "yref": "y"
      },
      {
        "type": "line",
        "y0": 0,
        "y1": 0,
        "xref": "paper",
        "x0": 0,
        "x1": 0.313333333333333,
        "line": {
          "color": "red",
          "dash": "dot"
        },
        "yref": "y2"
      },
      {
        "type": "line",
        "y0": 0,
        "y1": 0,
        "xref": "paper",
        "x0": 0.353333333333333,
        "x1": 0.646666666666667,
        "line": {
          "color": "red",
          "dash": "dot"
        },
        "yref": "y2"
      },
      {
        "type": "line",
        "y0": 0,
        "y1": 0,
        "xref": "paper",
        "x0": 0.686666666666667,
        "x1": 1,
        "line": {
          "color": "red",
          "dash": "dot"
        },
        "yref": "y2"
      }
    ],
    "images": [],
    "margin": {
      "b": 40,
      "l": 60,
      "t": 25,
      "r": 10
    },
    "hovermode": "closest",
    "showlegend": false
  },
  "attrs": {
    "69da5399400d": {
      "x": {},
      "y": {},
      "mode": "lines",
      "showlegend": false,
      "line": {
        "color": "red"
      },
      "hovertemplate": "<i>Year<i>: %{x} <br>Productivity Change: %{y:.3f}",
      "name": "Negative Shock<br>Low Productivity",
      "alpha_stroke": 1,
      "sizes": [10, 100],
      "spans": [1, 20],
      "type": "scatter"
    },
    "69da389d7935": {
      "x": {},
      "y": {},
      "mode": "lines",
      "showlegend": false,
      "line": {
        "color": "green"
      },
      "hovertemplate": "<i>Year<i>: %{x} <br>Productivity Change: %{y:.3f}",
      "name": "Negative Shock<br>Medium Productivity",
      "alpha_stroke": 1,
      "sizes": [10, 100],
      "spans": [1, 20],
      "type": "scatter"
    },
    "69da31c5d055": {
      "x": {},
      "y": {},
      "mode": "lines",
      "showlegend": false,
      "line": {
        "color": "blue"
      },
      "hovertemplate": "<i>Year<i>: %{x} <br>Productivity Change: %{y:.3f}",
      "name": "Negative Shock<br>High Productivity",
      "alpha_stroke": 1,
      "sizes": [10, 100],
      "spans": [1, 20],
      "type": "scatter"
    },
    "69da508866bc": {
      "x": {},
      "y": {},
      "mode": "lines",
      "showlegend": false,
      "line": {
        "color": "red"
      },
      "hovertemplate": "<i>Year<i>: %{x} <br>Productivity Change: %{y:.3f}",
      "name": "Positive Shock<br>Low Productivity",
      "alpha_stroke": 1,
      "sizes": [10, 100],
      "spans": [1, 20],
      "type": "scatter"
    },
    "69da1a42ab7e": {
      "x": {},
      "y": {},
      "mode": "lines",
      "showlegend": false,
      "line": {
        "color": "green"
      },
      "hovertemplate": "<i>Year<i>: %{x} <br>Productivity Change: %{y:.3f}",
      "name": "Positive Shock<br>Medium Productivity",
      "alpha_stroke": 1,
      "sizes": [10, 100],
      "spans": [1, 20],
      "type": "scatter"
    },
    "69da73005639": {
      "x": {},
      "y": {},
      "mode": "lines",
      "showlegend": false,
      "line": {
        "color": "blue"
      },
      "hovertemplate": "<i>Year<i>: %{x} <br>Productivity Change: %{y:.3f}",
      "name": "Positive Shock<br>High Productivity",
      "alpha_stroke": 1,
      "sizes": [10, 100],
      "spans": [1, 20],
      "type": "scatter"
    }
  },
  "source": "A",
  "config": {
    "showSendToCloud": false
  },
  "highlight": {
    "on": "plotly_click",
    "persistent": false,
    "dynamic": false,
    "selectize": false,
    "opacityDim": 0.2,
    "selected": {
      "opacity": 1
    },
    "debounce": 0
  },
  "subplot": true,
  "shinyEvents": ["plotly_hover", "plotly_click", "plotly_selected", "plotly_relayout", "plotly_brushed", "plotly_brushing", "plotly_clickannotation", "plotly_doubleclick", "plotly_deselect", "plotly_afterplot", "plotly_sunburstclick"],
  "base_url": "https://plot.ly"
}
